README.txt
setup.py
zopeskel.txt
docs/HISTORY.txt
teamrubber/__init__.py
teamrubber.snakeskin.egg-info/PKG-INFO
teamrubber.snakeskin.egg-info/SOURCES.txt
teamrubber.snakeskin.egg-info/dependency_links.txt
teamrubber.snakeskin.egg-info/entry_points.txt
teamrubber.snakeskin.egg-info/namespace_packages.txt
teamrubber.snakeskin.egg-info/not-zip-safe
teamrubber.snakeskin.egg-info/requires.txt
teamrubber.snakeskin.egg-info/top_level.txt
teamrubber/snakeskin/__init__.py
teamrubber/snakeskin/snakeskin.py
teamrubber/snakeskin/templates/snakeskin/+project+-configure.zcml_tmpl
teamrubber/snakeskin/templates/snakeskin/setup.py_tmpl
teamrubber/snakeskin/templates/snakeskin/+namespace_package+/+package+/configure.zcml_tmpl
teamrubber/snakeskin/templates/snakeskin/+namespace_package+/+package+/profiles.zcml_tmpl
teamrubber/snakeskin/templates/snakeskin/+namespace_package+/+package+/skins.zcml_tmpl
teamrubber/snakeskin/templates/snakeskin/+namespace_package+/+package+/Extensions/Install.py_tmpl
teamrubber/snakeskin/templates/snakeskin/+namespace_package+/+package+/browser/__init__.py
teamrubber/snakeskin/templates/snakeskin/+namespace_package+/+package+/browser/configure.zcml_tmpl
teamrubber/snakeskin/templates/snakeskin/+namespace_package+/+package+/browser/interfaces.py_tmpl
teamrubber/snakeskin/templates/snakeskin/+namespace_package+/+package+/browser/images/README.txt_tmpl
teamrubber/snakeskin/templates/snakeskin/+namespace_package+/+package+/browser/stylesheets/README.txt_tmpl
teamrubber/snakeskin/templates/snakeskin/+namespace_package+/+package+/browser/stylesheets/main.css_tmpl
teamrubber/snakeskin/templates/snakeskin/+namespace_package+/+package+/profiles/default/cssregistry.xml_tmpl
teamrubber/snakeskin/templates/snakeskin/+namespace_package+/+package+/profiles/default/metadata.xml_tmpl
teamrubber/snakeskin/templates/snakeskin/+namespace_package+/+package+/profiles/default/skins.xml_tmpl
teamrubber/snakeskin/templates/snakeskin/+namespace_package+/+package+/profiles/uninstall/skins.xml_tmpl
teamrubber/snakeskin/templates/snakeskin/+namespace_package+/+package+/skins/+namespace_package+_+package+_images/CONTENTS.txt_tmpl
teamrubber/snakeskin/templates/snakeskin/+namespace_package+/+package+/skins/+namespace_package+_+package+_scripts/CONTENTS.txt_tmpl
