Metadata-Version: 1.0
Name: teamrubber.snakeskin
Version: 1.1
Summary: A paster template for creating derivative themes.
Home-page: http://www.teamrubber.com
Author: Matthew Wilkes
Author-email: matt.wilkes@teamrubber.com
License: GPL
Platform: UNKNOWN
Classifier: Programming Language :: Python
Classifier: Topic :: Software Development :: Libraries :: Python Modules
